LICENSE
README.md
setup.py
mkdocs_statblock_plugin/__init__.py
mkdocs_statblock_plugin/mkdocs_statblock_plugin.py
mkdocs_statblock_plugin/statblock_handler.py
mkdocs_statblock_plugin.egg-info/PKG-INFO
mkdocs_statblock_plugin.egg-info/SOURCES.txt
mkdocs_statblock_plugin.egg-info/dependency_links.txt
mkdocs_statblock_plugin.egg-info/entry_points.txt
mkdocs_statblock_plugin.egg-info/requires.txt
mkdocs_statblock_plugin.egg-info/top_level.txt