Metadata-Version: 2.1
Name: mkdocs_statblock_plugin
Version: 0.1.3
Summary: MkDocs plugin to format YAML within statblock superfences as HTML
Home-page: https://github.com/johannes-z/mkdocs-statblock-plugin.git
Author: Johannes Zwirchmayr
Author-email: johannes.zwirchmayr@gmail.com
Requires-Python: >=3.6
License-File: LICENSE
Requires-Dist: mkdocs>=1.6.0
Requires-Dist: pyyaml
